discord_gateway/__init__.py
discord_gateway/conn.py
discord_gateway/errors.py
discord_gateway/opcode.py
discord_gateway/py.typed
discord_gateway-0.4.0.dist-info/LICENSE
discord_gateway-0.4.0.dist-info/WHEEL
discord_gateway-0.4.0.dist-info/METADATA
discord_gateway-0.4.0.dist-info/RECORD
