Metadata-Version: 2.1
Name: discord-gateway
Version: 0.4.0
Summary: Sans-I/O implementation of the Discord gateway
Keywords: discord,discord-api,discord-bot,discord-api-wrapper,discord-gateway,python-3
Author-email: Bluenix <bluenixdev@gmail.com>
Requires-Python: >=3.6.2
Classifier: Development Status :: 4 - Beta
Classifier: Intended Audience :: Developers
Classifier: License :: OSI Approved :: MIT License
Classifier: Natural Language :: English
Classifier: Operating System :: OS Independent
Classifier: Programming Language :: Python
Classifier: Programming Language :: Python :: 3
Classifier: Programming Language :: Python :: 3 :: Only
Classifier: Programming Language :: Python :: 3.6
Classifier: Programming Language :: Python :: 3.7
Classifier: Programming Language :: Python :: 3.8
Classifier: Programming Language :: Python :: 3.9
Classifier: Programming Language :: Python :: 3.10
Classifier: Topic :: Internet
Classifier: Topic :: Internet :: WWW/HTTP
Classifier: Topic :: Software Development :: Libraries
Classifier: Topic :: Software Development :: Libraries :: Python Modules
Classifier: Typing :: Typed
Requires-Dist: wsproto >= 1.0.0, <2
Project-URL: homepage, https://github.com/Bluenix2/discord-gateway/
Project-URL: repository, https://github.com/Bluenix2/discord-gateway/
